DailyTools/DailyTools.py
DailyTools/__init__.py
DailyTools-0.7.0.dist-info/LICENSE
DailyTools-0.7.0.dist-info/METADATA
DailyTools-0.7.0.dist-info/WHEEL
DailyTools-0.7.0.dist-info/top_level.txt
DailyTools-0.7.0.dist-info/RECORD
