Metadata-Version: 2.1
Name: DailyTools
Version: 0.7.0
Summary: My short description for my project.
Home-page: https://blog.csdn.net/qq_39295540
Author: Casey
Author-email: 395280963@qq.com
License: MIT
Platform: UNKNOWN
Classifier: License :: OSI Approved :: MIT License
Classifier: Programming Language :: Python
Classifier: Programming Language :: Python :: 3
Classifier: Programming Language :: Python :: 3.6
Classifier: Programming Language :: Python :: Implementation :: CPython
Classifier: Programming Language :: Python :: Implementation :: PyPy
Requires-Python: >=3.6.0
Requires-Dist: pymysql
Requires-Dist: DBUtils
Requires-Dist: pyforest
Requires-Dist: httpx
Requires-Dist: ddddocr
Requires-Dist: loguru
Requires-Dist: requests
